{
  "url": "https://www.getsunday.com/shop/garden/globosa-nana-cryptomeria",
  "product_slug": "globosa-nana-cryptomeria",
  "product_name": "Globosa Nana Cryptomeria",
  "description": null,
  "sections": {},
  "image_url": "https://cdn.sanity.io/images/afv8yn22/production/cc757d47d52c62674d725b591aad067ec0977290-2400x2400.jpg?w=1000&h=1000&fit=crop&auto=format&dpr=1",
  "image_path": "data\\images\\globosa-nana-cryptomeria.png",
  "scraped_at_utc": "2026-01-19T17:26:23.488608+00:00",
  "product_url": "https://www.getsunday.com/shop/garden/globosa-nana-cryptomeria"
}